{
  "categories": [
    "biegi",
    "emocje",
    "portret",
    "krajobraz",
    "więcej",
    "o mnie",
    "sklep"
  ],

  "dropdownCategories": ["z lotu ptaka", "wydarzenia", "portret", "inne"],
  "imagesWelcome": [
    {
      "id": "c9904ea3-7d9b-4215-a868-7b4060f18fd0",
      "title": "",
      "description": "",
      "thumbnail": "../assets/portfolio/biegi/0.jpg",
      "url": "../assets/portfolio/biegi/0.jpg",
      "album": "biegi",
      "location": "Brzozów",
      "event": "Bieg Rzeźnika",
      "date": "2022-11-11",
      "price": 15
    },
    {
      "title": "",
      "description": "",
      "thumbnail": "../assets/portfolio/top/1.jpg",
      "url": "../assets/portfolio/top/1.jpg",
      "category": "biegi",
      "location": "",
      "event": "",
      "price": null
    },
    {
      "title": "",
      "description": "",
      "thumbnail": "../assets/portfolio/top/2.jpg",
      "url": "../assets/portfolio/top/2.jpg",
      "category": "biegi",
      "location": "",
      "event": "",
      "price": null
    },
    {
      "title": "",
      "description": "",
      "thumbnail": "../assets/portfolio/top/3.jpg",
      "url": "../assets/portfolio/top/4.jpg",
      "category": "biegi",
      "location": "",
      "event": "",
      "price": null
    },
    {
      "title": "",
      "description": "",
      "thumbnail": "../assets/portfolio/top/5.jpg",
      "url": "../assets/portfolio/top/6.jpg",
      "category": "biegi",
      "location": "",
      "event": "",
      "price": null
    },
    {
      "title": "",
      "description": "",
      "thumbnail": "../assets/portfolio/top/7.jpg",
      "url": "../assets/portfolio/top/8.jpg",
      "category": "biegi",
      "location": "",
      "event": "",
      "price": null
    },
    {
      "title": "",
      "description": "",
      "thumbnail": "../assets/portfolio/top/9.jpg",
      "url": "../assets/portfolio/top/9.jpg",
      "category": "biegi",
      "location": "",
      "event": "",
      "price": null
    },
    {
      "title": "",
      "description": "",
      "thumbnail": "../assets/portfolio/top/10.jpg",
      "url": "../assets/portfolio/top/10.jpg",
      "category": "biegi",
      "location": "",
      "event": "",
      "price": null
    },
    {
      "title": "",
      "description": "",
      "thumbnail": "../assets/portfolio/top/11.jpg",
      "url": "../assets/portfolio/top/11.jpg",
      "category": "biegi",
      "location": "",
      "event": "",
      "price": null
    },
    {
      "title": "",
      "description": "",
      "thumbnail": "../assets/portfolio/top/12.jpg",
      "url": "../assets/portfolio/top/12.jpg",
      "category": "biegi",
      "location": "",
      "event": "",
      "price": null
    }
  ],

  "images": [
    {
      "title": "",
      "description": "Kwintesencja Trail Runningu, Wbiegnij na PODIUM z Buty Jana 2022",
      "thumbnail": "../assets/portfolio/biegi/0.jpg",
      "url": "../assets/portfolio/biegi/0.jpg",
      "category": "biegi",
      "location": "",
      "event": "",
      "price": null
    },
    {
      "title": "",
      "description": "Krzysztof Wiernusz, zwycięzca biegu 50km UltraPrzesilenie, 2022",
      "thumbnail": "../assets/portfolio/biegi/1.jpg",
      "url": "../assets/portfolio/biegi/1.jpg",
      "category": "biegi",
      "location": "",
      "event": "",
      "price": null
    },
    {
      "title": "",
      "description": "Zawadzka Team, zawsze uśmiechnięte na trasie",
      "thumbnail": "../assets/portfolio/biegi/2.jpg",
      "url": "../assets/portfolio/biegi/2.jpg",
      "category": "biegi",
      "location": "",
      "event": "",
      "price": null
    },
    {
      "title": "",
      "description": "Ostatnia edycja Ultramaratonu Podkarpackiego 2022 [*]",
      "thumbnail": "../assets/portfolio/biegi/3.jpg",
      "url": "../assets/portfolio/biegi/3.jpg",
      "category": "biegi",
      "location": "",
      "event": "",
      "price": null
    },
    {
      "title": "",
      "description": "Pogórze Ultra Trial 2022",
      "thumbnail": "../assets/portfolio/biegi/4.jpg",
      "url": "../assets/portfolio/biegi/4.jpg",
      "category": "biegi",
      "location": "",
      "event": "",
      "price": null
    },
    {
      "title": "",
      "description": "Ultramaraton JagaKora",
      "thumbnail": "../assets/portfolio/biegi/5.jpg",
      "url": "../assets/portfolio/biegi/5.jpg",
      "category": "biegi",
      "location": "",
      "event": "",
      "price": null
    },
    {
      "title": "",
      "description": "Półmaraton Biegam i Wspieram, Budy Głogowskie",
      "thumbnail": "../assets/portfolio/biegi/6.jpg",
      "url": "../assets/portfolio/biegi/6.jpg",
      "category": "biegi",
      "location": "",
      "event": "",
      "price": null
    },
    {
      "title": "",
      "description": "Biegi Górskie Sanok",
      "thumbnail": "../assets/portfolio/biegi/7.jpg",
      "url": "../assets/portfolio/biegi/7.jpg",
      "category": "biegi",
      "location": "",
      "event": "",
      "price": null
    },
    {
      "title": "",
      "description": "Biegi Górskie Sanok",
      "thumbnail": "../assets/portfolio/biegi/8.jpg",
      "url": "../assets/portfolio/biegi/8.jpg",
      "category": "biegi",
      "location": "",
      "event": "",
      "price": null
    },
    {
      "title": "",
      "description": "Ultra przesilenie Dynów",
      "thumbnail": "../assets/portfolio/biegi/9.jpg",
      "url": "../assets/portfolio/biegi/9.jpg",
      "category": "biegi",
      "location": "",
      "event": "",
      "price": null
    },
    {
      "title": "",
      "description": "Pogórze Ultra Trial",
      "thumbnail": "../assets/portfolio/biegi/10.jpg",
      "url": "../assets/portfolio/biegi/10.jpg",
      "category": "biegi",
      "location": "",
      "event": "",
      "price": null
    },
    {
      "title": "",
      "description": "Ultramaraton Jaga-Kora",
      "thumbnail": "../assets/portfolio/biegi/11.jpg",
      "url": "../assets/portfolio/biegi/11.jpg",
      "category": "biegi",
      "location": "",
      "event": "",
      "price": null
    },
    {
      "title": "",
      "description": "Bieg Kolorowej Skarpetki Rzeszów",
      "thumbnail": "../assets/portfolio/biegi/12.jpg",
      "url": "../assets/portfolio/biegi/12.jpg",
      "category": "biegi",
      "location": "",
      "event": "",
      "price": null
    },
    {
      "title": "",
      "description": "Lasy na Biegi Górskie Sanok",
      "thumbnail": "../assets/portfolio/biegi/13.jpg",
      "url": "../assets/portfolio/biegi/13.jpg",
      "category": "biegi",
      "location": "",
      "event": "",
      "price": null
    },
    {
      "title": "",
      "description": "Punkt Widokowy Ultramaraton Jaga-Kora",
      "thumbnail": "../assets/portfolio/biegi/14.jpg",
      "url": "../assets/portfolio/biegi/14.jpg",
      "category": "biegi",
      "location": "",
      "event": "",
      "price": null
    },
    {
      "title": "",
      "description": "Punkt Widokowy Ultramaraton Jaga-Kora",
      "thumbnail": "../assets/portfolio/biegi/15.jpg",
      "url": "../assets/portfolio/biegi/15.jpg",
      "category": "biegi",
      "location": "",
      "event": "",
      "price": null
    },
    {
      "title": "",
      "description": "Ultramaraton Podkarpacki 2022",
      "thumbnail": "../assets/portfolio/biegi/16.jpg",
      "url": "../assets/portfolio/biegi/16.jpg",
      "category": "biegi",
      "location": "",
      "event": "",
      "price": null
    },
    {
      "title": "",
      "description": "Biegi Hrabiego Łańcut",
      "thumbnail": "../assets/portfolio/biegi/17.jpg",
      "url": "../assets/portfolio/biegi/17.jpg",
      "category": "biegi",
      "location": "",
      "event": "",
      "price": null
    },
    {
      "title": "",
      "description": "Meta Triathlon Sokoła",
      "thumbnail": "../assets/portfolio/emocje/0.jpg",
      "url": "../assets/portfolio/emocje/0.jpg",
      "category": "emocje",
      "location": "",
      "event": "",
      "price": null
    },
    {
      "title": "",
      "description": "Pogórze Ultra Trial",
      "thumbnail": "../assets/portfolio/emocje/1.jpg",
      "url": "../assets/portfolio/emocje/1.jpg",
      "category": "emocje",
      "location": "",
      "event": "",
      "price": null
    },
    {
      "title": "",
      "description": "Wzruszający moment, Ultramaraton Podkarpacki",
      "thumbnail": "../assets/portfolio/emocje/2.jpg",
      "url": "../assets/portfolio/emocje/2.jpg",
      "category": "emocje",
      "location": "",
      "event": "",
      "price": null
    },
    {
      "title": "",
      "description": "Obraz szczęścia na mecie, PUT2022",
      "thumbnail": "../assets/portfolio/emocje/3.jpg",
      "url": "../assets/portfolio/emocje/3.jpg",
      "category": "emocje",
      "location": "",
      "event": "",
      "price": null
    },
    {
      "title": "",
      "description": "Nie ma nic piękniejszego niż wsparcie rodziny PUT2022",
      "thumbnail": "../assets/portfolio/emocje/4.jpg",
      "url": "../assets/portfolio/emocje/4.jpg",
      "category": "emocje",
      "location": "",
      "event": "",
      "price": null
    },
    {
      "title": "",
      "description": "Wzruszenie, satysfakcja PUT2022",
      "thumbnail": "../assets/portfolio/emocje/5.jpg",
      "url": "../assets/portfolio/emocje/5.jpg",
      "category": "emocje",
      "location": "",
      "event": "",
      "price": null
    },
    {
      "title": "",
      "description": "Pierwsze Ultra, Ultramaraton Podkarpacki 2022",
      "thumbnail": "../assets/portfolio/emocje/6.jpg",
      "url": "../assets/portfolio/emocje/6.jpg",
      "category": "emocje",
      "location": "",
      "event": "",
      "price": null
    },
    {
      "title": "",
      "description": "W uścisku przyjaciółki PUT2022",
      "thumbnail": "../assets/portfolio/emocje/7.jpg",
      "url": "../assets/portfolio/emocje/7.jpg",
      "category": "emocje",
      "location": "",
      "event": "",
      "price": null
    },
    {
      "title": "",
      "description": "Doping syna. Triathlon Sokoła",
      "thumbnail": "../assets/portfolio/emocje/8.jpg",
      "url": "../assets/portfolio/emocje/8.jpg",
      "category": "emocje",
      "location": "",
      "event": "",
      "price": null
    },
    {
      "title": "",
      "description": "Meta Pogórze Ultra Trial",
      "thumbnail": "../assets/portfolio/emocje/9.jpg",
      "url": "../assets/portfolio/emocje/9.jpg",
      "category": "emocje",
      "location": "",
      "event": "",
      "price": null
    },
    {
      "title": "",
      "description": "Nie zawsze jest kolorowo, PUT2022",
      "thumbnail": "../assets/portfolio/emocje/10.jpg",
      "url": "../assets/portfolio/emocje/10.jpg",
      "category": "emocje",
      "location": "",
      "event": "",
      "price": null
    },
    {
      "title": "",
      "description": "",
      "thumbnail": "../assets/portfolio/portret/0.jpg",
      "url": "../assets/portfolio/portret/0.jpg",
      "category": "portret",
      "location": "",
      "event": "",
      "price": null
    },
    {
      "title": "",
      "description": "",
      "thumbnail": "../assets/portfolio/portret/1.jpg",
      "url": "../assets/portfolio/portret/1.jpg",
      "category": "portret",
      "location": "",
      "event": "",
      "price": null
    },
    {
      "title": "",
      "description": "",
      "thumbnail": "../assets/portfolio/portret/2.jpg",
      "url": "../assets/portfolio/portret/2.jpg",
      "category": "portret",
      "location": "",
      "event": "",
      "price": null
    },
    {
      "title": "",
      "description": "",
      "thumbnail": "../assets/portfolio/portret/3.jpg",
      "url": "../assets/portfolio/portret/3.jpg",
      "category": "portret",
      "location": "",
      "event": "",
      "price": null
    },
    {
      "title": "",
      "description": "",
      "thumbnail": "../assets/portfolio/portret/4.jpg",
      "url": "../assets/portfolio/portret/4.jpg",
      "category": "portret",
      "location": "",
      "event": "",
      "price": null
    },
    {
      "title": "",
      "description": "",
      "thumbnail": "../assets/portfolio/portret/5.jpg",
      "url": "../assets/portfolio/portret/5.jpg",
      "category": "portret",
      "location": "",
      "event": "",
      "price": null
    },
    {
      "title": "",
      "description": "",
      "thumbnail": "../assets/portfolio/portret/6.jpg",
      "url": "../assets/portfolio/portret/6.jpg",
      "category": "portret",
      "location": "",
      "event": "",
      "price": null
    },
    {
      "title": "",
      "description": "",
      "thumbnail": "../assets/portfolio/portret/7.jpg",
      "url": "../assets/portfolio/portret/7.jpg",
      "category": "portret",
      "location": "",
      "event": "",
      "price": null
    },
    {
      "title": "",
      "description": "",
      "thumbnail": "../assets/portfolio/portret/8.jpg",
      "url": "../assets/portfolio/portret/8.jpg",
      "category": "portret",
      "location": "",
      "event": "",
      "price": null
    },
    {
      "title": "",
      "description": "",
      "thumbnail": "../assets/portfolio/portret/9.jpg",
      "url": "../assets/portfolio/portret/9.jpg",
      "category": "portret",
      "location": "",
      "event": "",
      "price": null
    },
    {
      "title": "",
      "description": "",
      "thumbnail": "../assets/portfolio/krajobraz/0.jpg",
      "url": "../assets/portfolio/krajobraz/0.jpg",
      "category": "krajobraz",
      "location": "",
      "event": "",
      "price": null
    },
    {
      "title": "",
      "description": "",
      "thumbnail": "../assets/portfolio/krajobraz/1.jpg",
      "url": "../assets/portfolio/krajobraz/1.jpg",
      "category": "krajobraz",
      "location": "",
      "event": "",
      "price": null
    },
    {
      "title": "",
      "description": "",
      "thumbnail": "../assets/portfolio/krajobraz/2.jpg",
      "url": "../assets/portfolio/krajobraz/2.jpg",
      "category": "krajobraz",
      "location": "",
      "event": "",
      "price": null
    },
    {
      "title": "",
      "description": "",
      "thumbnail": "../assets/portfolio/krajobraz/3.jpg",
      "url": "../assets/portfolio/krajobraz/3.jpg",
      "category": "krajobraz",
      "location": "",
      "event": "",
      "price": null
    },
    {
      "title": "",
      "description": "",
      "thumbnail": "../assets/portfolio/krajobraz/4.jpg",
      "url": "../assets/portfolio/krajobraz/4.jpg",
      "category": "krajobraz",
      "location": "",
      "event": "",
      "price": null
    },
    {
      "title": "",
      "description": "",
      "thumbnail": "../assets/portfolio/krajobraz/5.jpg",
      "url": "../assets/portfolio/krajobraz/5.jpg",
      "category": "krajobraz",
      "location": "",
      "event": "",
      "price": null
    },
    {
      "title": "",
      "description": "",
      "thumbnail": "../assets/portfolio/krajobraz/6.jpg",
      "url": "../assets/portfolio/krajobraz/6.jpg",
      "category": "krajobraz",
      "location": "",
      "event": "",
      "price": null
    },
    {
      "title": "",
      "description": "",
      "thumbnail": "../assets/portfolio/krajobraz/7.jpg",
      "url": "../assets/portfolio/krajobraz/7.jpg",
      "category": "krajobraz",
      "location": "",
      "event": "",
      "price": null
    },
    {
      "title": "",
      "description": "",
      "thumbnail": "../assets/portfolio/krajobraz/8.jpg",
      "url": "../assets/portfolio/krajobraz/8.jpg",
      "category": "krajobraz",
      "location": "",
      "event": "",
      "price": null
    },
    {
      "title": "",
      "description": "Grand Chotowa Triathlon",
      "thumbnail": "../assets/portfolio/inne/1.jpg",
      "url": "../assets/portfolio/inne/1.jpg",
      "category": "więcej",
      "location": "",
      "event": "",
      "price": null
    },
    {
      "title": "",
      "description": "Prima Akademia Rzeszów. Spacer po kładce.",
      "thumbnail": "../assets/portfolio/inne/2.jpg",
      "url": "../assets/portfolio/inne/2.jpg",
      "category": "więcej",
      "location": "",
      "event": "",
      "price": null
    },
    {
      "title": "",
      "description": "Byle do mety!",
      "thumbnail": "../assets/portfolio/inne/3.jpg",
      "url": "../assets/portfolio/inne/3.jpg",
      "category": "więcej",
      "location": "",
      "event": "",
      "price": null
    },
    {
      "title": "",
      "description": "Bieszczady o wschodzie",
      "thumbnail": "../assets/portfolio/inne/4.jpg",
      "url": "../assets/portfolio/inne/4.jpg",
      "category": "więcej",
      "location": "",
      "event": "",
      "price": null
    },
    {
      "title": "",
      "description": "Triathlon Sokoła",
      "thumbnail": "../assets/portfolio/inne/5.jpg",
      "url": "../assets/portfolio/inne/5.jpg",
      "category": "więcej",
      "location": "",
      "event": "",
      "price": null
    },
    {
      "title": "",
      "description": "Gminne dożynki Sokołów Małopolski",
      "thumbnail": "../assets/portfolio/inne/6.jpg",
      "url": "../assets/portfolio/inne/6.jpg",
      "category": "więcej",
      "location": "",
      "event": "",
      "price": null
    },
    {
      "title": "",
      "description": "Odprawa - Grand Chotowa Triathlon",
      "thumbnail": "../assets/portfolio/inne/7.jpg",
      "url": "../assets/portfolio/inne/7.jpg",
      "category": "więcej",
      "location": "",
      "event": "",
      "price": null
    },
    {
      "title": "",
      "description": "Kawa Pogórza - Natura wie co dobre",
      "thumbnail": "../assets/portfolio/inne/8.jpg",
      "url": "../assets/portfolio/inne/8.jpg",
      "category": "więcej",
      "location": "",
      "event": "",
      "price": null
    },
    {
      "title": "",
      "description": "Byle przed siebie",
      "thumbnail": "../assets/portfolio/inne/9.jpg",
      "url": "../assets/portfolio/inne/9.jpg",
      "isVertical": true,
      "category": "więcej",
      "location": "",
      "event": "",
      "price": null
    },
    {
      "title": "",
      "description": "Bieszczady o wschodzie",
      "thumbnail": "../assets/portfolio/inne/10.jpg",
      "url": "../assets/portfolio/inne/10.jpg",
      "category": "więcej",
      "location": "",
      "event": "",
      "price": null
    }
  ]
}
